bayesian_inference/__init__.py
bayesian_inference/entity/__init__.py
bayesian_inference/entity/bayesian_network.py
bayesian_inference/entity/network_node.py
bayesian_inference/entity/unit_test.py
bayesian_inference/exceptions/__init__.py
bayesian_inference/exceptions/exceptions.py
bayesian_inference/input_parser/__init__.py
bayesian_inference/input_parser/input_parser.py
bayesian_inference/input_parser/unit_test.py
bayesian_inference/probability/__init__.py
bayesian_inference/probability/probability.py
bayesian_inference/probability/unit_test.py
bayesian_inference-1.0.2.dist-info/LICENSE
bayesian_inference-1.0.2.dist-info/METADATA
bayesian_inference-1.0.2.dist-info/WHEEL
bayesian_inference-1.0.2.dist-info/top_level.txt
bayesian_inference-1.0.2.dist-info/RECORD
