Metadata-Version: 2.1
Name: bayesian-inference
Version: 1.0.2
Summary: Bayesian Inference library over network
Home-page: https://github.com/yakuza8/bayesian-inference
Author: Berat Cankar
Author-email: berat.cankar@gmail.com
License: UNKNOWN
Platform: UNKNOWN
Classifier: Programming Language :: Python :: 3
Classifier: License :: OSI Approved :: MIT License
Classifier: Operating System :: OS Independent
Requires-Python: >=3.7.3
Requires-Dist: coverage (~=5.2)
Requires-Dist: tabulate (~=0.8.7)
Requires-Dist: networkx (~=2.4)
